cheader2json/__main__.py
cheader2json/_version.py
cheader2json/change_search.py
cheader2json/cheader_reader.py
cheader2json-0.0.0rc2.dist-info/METADATA
cheader2json-0.0.0rc2.dist-info/WHEEL
cheader2json-0.0.0rc2.dist-info/entry_points.txt
cheader2json-0.0.0rc2.dist-info/top_level.txt
cheader2json-0.0.0rc2.dist-info/RECORD
