Metadata-Version: 2.1
Name: cheader2json
Version: 0.0.0rc2
Summary: Parse C header file and output JSON ast + types
Author-email: Ryan Mast <mast9@llnl.gov>, Andy Fisher <andrew.fisher@pnnl.gov>
Maintainer-email: Ryan Mast <mast9@llnl.gov>
License: BSD License
Project-URL: Homepage, https://github.com/GMLC-TDC/cheader2json
Project-URL: Issue Tracker, https://github.com/GMLC-TDC/cheader2json/issues
Project-URL: Source Code, https://github.com/GMLC-TDC/cheader2json
Keywords: libclang,clang,c,header,parser,json,conversion
Classifier: Programming Language :: Python :: 3
Classifier: Programming Language :: Python :: 3 :: Only
Classifier: Programming Language :: Python :: 3.8
Classifier: Programming Language :: Python :: 3.9
Classifier: Programming Language :: Python :: 3.10
Classifier: Programming Language :: Python :: 3.11
Classifier: Programming Language :: Python :: 3.12
Classifier: Development Status :: 2 - Pre-Alpha
Classifier: Environment :: Console
Classifier: Operating System :: MacOS
Classifier: Operating System :: Microsoft :: Windows
Classifier: Operating System :: POSIX :: Linux
Classifier: Topic :: Software Development
Classifier: Topic :: System
Classifier: Topic :: Utilities
Classifier: License :: OSI Approved :: BSD License
Requires-Python: >=3.8
Requires-Dist: libclang ==18.1.1
Requires-Dist: click
Provides-Extra: dev
Requires-Dist: build ; extra == 'dev'
Requires-Dist: pre-commit ; extra == 'dev'
Provides-Extra: docs
Requires-Dist: sphinx ; extra == 'docs'
Requires-Dist: myst-parser ; extra == 'docs'
Provides-Extra: test
Requires-Dist: pytest ; extra == 'test'
